{
  "pair_results": {
    "(0,1)": {
      "group_A": 0,
      "group_B": 1,
      "party_A": 1,
      "party_B": 0,
      "same_party": false,
      "total_interaction": 474,
      "pattern": "Stability",
      "slope": 0.0018747657537460337,
      "intercept": 0.4618677645921707,
      "r_squared": 0.001202124901631067,
      "p_value": 0.919390193568677,
      "diff_mean": 0.4712415933609009,
      "diff_std": 0.17099060118198395,
      "diff_start": 0.38855189085006714,
      "diff_end": 0.3801456093788147,
      "ab_corr_p": 0.5273773117496685,
      "ba_corr_p": 0.8464537978892663,
      "contagion_direction": null
    },
    "(0,2)": {
      "group_A": 0,
      "group_B": 2,
      "party_A": 1,
      "party_B": 0,
      "same_party": false,
      "total_interaction": 1170,
      "pattern": "Convergence",
      "slope": -0.020214119282635775,
      "intercept": 0.448913110928102,
      "r_squared": 0.3665535616791477,
      "p_value": 0.04839584078150508,
      "diff_mean": 0.3478425145149231,
      "diff_std": 0.10558108985424042,
      "diff_start": 0.45080018043518066,
      "diff_end": 0.205551415681839,
      "ab_corr_p": 0.32317022898538816,
      "ba_corr_p": 0.8705563993026687,
      "contagion_direction": null
    },
    "(0,3)": {
      "group_A": 0,
      "group_B": 3,
      "party_A": 1,
      "party_B": 1,
      "same_party": true,
      "total_interaction": 4741,
      "pattern": "Stability",
      "slope": -0.018361659212545917,
      "intercept": 0.25198849222876807,
      "r_squared": 0.2708842536903406,
      "p_value": 0.10072182208572095,
      "diff_mean": 0.1601801961660385,
      "diff_std": 0.11156296730041504,
      "diff_start": 0.2140793800354004,
      "diff_end": 0.11212846636772156,
      "ab_corr_p": 0.916894075363082,
      "ba_corr_p": 0.7725211414965671,
      "contagion_direction": null
    },
    "(0,4)": {
      "group_A": 0,
      "group_B": 4,
      "party_A": 1,
      "party_B": 1,
      "same_party": true,
      "total_interaction": 1740,
      "pattern": "Stability",
      "slope": 0.006093986196951433,
      "intercept": 0.044572652063586495,
      "r_squared": 0.10004308161467212,
      "p_value": 0.34332673577964723,
      "diff_mean": 0.07504258304834366,
      "diff_std": 0.06092673912644386,
      "diff_start": 0.13735932111740112,
      "diff_end": 0.1782398521900177,
      "ab_corr_p": 0.9338682262475769,
      "ba_corr_p": 0.8003064345881515,
      "contagion_direction": null
    },
    "(0,5)": {
      "group_A": 0,
      "group_B": 5,
      "party_A": 1,
      "party_B": 0,
      "same_party": false,
      "total_interaction": 229,
      "pattern": "Convergence",
      "slope": -0.04706827700138092,
      "intercept": 0.6381750255823135,
      "r_squared": 0.4635888384354237,
      "p_value": 0.02109041757632547,
      "diff_mean": 0.40283364057540894,
      "diff_std": 0.2186058610677719,
      "diff_start": 0.3524757921695709,
      "diff_end": 0.1483003795146942,
      "ab_corr_p": 0.7600989396362694,
      "ba_corr_p": 0.46537688927399684,
      "contagion_direction": null
    },
    "(0,6)": {
      "group_A": 0,
      "group_B": 6,
      "party_A": 1,
      "party_B": 0,
      "same_party": false,
      "total_interaction": 2631,
      "pattern": "Stability",
      "slope": 0.0006098403172059493,
      "intercept": 0.4211865297772668,
      "r_squared": 0.0008561905402004092,
      "p_value": 0.9319428887938214,
      "diff_mean": 0.4242357313632965,
      "diff_std": 0.06590690463781357,
      "diff_start": 0.33159396052360535,
      "diff_end": 0.39518317580223083,
      "ab_corr_p": 0.7635741018292965,
      "ba_corr_p": 0.8537381822813951,
      "contagion_direction": null
    },
    "(1,0)": {
      "group_A": 1,
      "group_B": 0,
      "party_A": 0,
      "party_B": 1,
      "same_party": false,
      "total_interaction": 474,
      "pattern": "Stability",
      "slope": 0.0018747657537460337,
      "intercept": 0.4618677645921707,
      "r_squared": 0.001202124901631067,
      "p_value": 0.919390193568677,
      "diff_mean": 0.4712415933609009,
      "diff_std": 0.17099060118198395,
      "diff_start": 0.38855189085006714,
      "diff_end": 0.3801456093788147,
      "ab_corr_p": 0.8464537978892663,
      "ba_corr_p": 0.5273773117496685,
      "contagion_direction": null
    },
    "(1,2)": {
      "group_A": 1,
      "group_B": 2,
      "party_A": 0,
      "party_B": 0,
      "same_party": true,
      "total_interaction": 2532,
      "pattern": "Stability",
      "slope": 0.011982166902585464,
      "intercept": 0.08789539269425652,
      "r_squared": 0.1818909547564836,
      "p_value": 0.19084871455346866,
      "diff_mean": 0.14780622720718384,
      "diff_std": 0.08884435147047043,
      "diff_start": 0.062248289585113525,
      "diff_end": 0.17459417879581451,
      "ab_corr_p": 0.6088357543212769,
      "ba_corr_p": 0.6044177807237481,
      "contagion_direction": null
    },
    "(1,3)": {
      "group_A": 1,
      "group_B": 3,
      "party_A": 0,
      "party_B": 1,
      "same_party": false,
      "total_interaction": 1727,
      "pattern": "Stability",
      "slope": -0.008100782470269637,
      "intercept": 0.6203306845643304,
      "r_squared": 0.023378311105982572,
      "p_value": 0.6535580190025307,
      "diff_mean": 0.5798267722129822,
      "diff_std": 0.16754072904586792,
      "diff_start": 0.6026312708854675,
      "diff_end": 0.49227404594421387,
      "ab_corr_p": 0.5795253998251265,
      "ba_corr_p": 0.8976188055399844,
      "contagion_direction": null
    },
    "(1,4)": {
      "group_A": 1,
      "group_B": 4,
      "party_A": 0,
      "party_B": 1,
      "same_party": false,
      "total_interaction": 104,
      "pattern": "Stability",
      "slope": 0.025581514022567052,
      "intercept": 0.35341033745895734,
      "r_squared": 0.2451430829408968,
      "p_value": 0.12150584741547686,
      "diff_mean": 0.4813179075717926,
      "diff_std": 0.16338659822940826,
      "diff_start": 0.251192569732666,
      "diff_end": 0.55838543176651,
      "ab_corr_p": 0.28132428636202356,
      "ba_corr_p": 0.6279607728838444,
      "contagion_direction": null
    },
    "(1,5)": {
      "group_A": 1,
      "group_B": 5,
      "party_A": 0,
      "party_B": 0,
      "same_party": true,
      "total_interaction": 168,
      "pattern": "Stability",
      "slope": 0.015857798335227095,
      "intercept": 0.10905001820488411,
      "r_squared": 0.16429088123029986,
      "p_value": 0.21618954691807535,
      "diff_mean": 0.1883390098810196,
      "diff_std": 0.12371893227100372,
      "diff_start": 0.036076098680496216,
      "diff_end": 0.2318452149629593,
      "ab_corr_p": 0.7313286398131,
      "ba_corr_p": 0.553911243017114,
      "contagion_direction": null
    },
    "(1,6)": {
      "group_A": 1,
      "group_B": 6,
      "party_A": 0,
      "party_B": 0,
      "same_party": true,
      "total_interaction": 5006,
      "pattern": "Stability",
      "slope": -0.014925644140351904,
      "intercept": 0.20052071085030382,
      "r_squared": 0.21150912988781173,
      "p_value": 0.15465811618776162,
      "diff_mean": 0.1258924901485443,
      "diff_std": 0.10262862592935562,
      "diff_start": 0.05695793032646179,
      "diff_end": 0.015037573873996735,
      "ab_corr_p": 0.6747385355530675,
      "ba_corr_p": 0.8385378872804171,
      "contagion_direction": null
    },
    "(2,0)": {
      "group_A": 2,
      "group_B": 0,
      "party_A": 0,
      "party_B": 1,
      "same_party": false,
      "total_interaction": 1170,
      "pattern": "Convergence",
      "slope": -0.020214119282635775,
      "intercept": 0.448913110928102,
      "r_squared": 0.3665535616791477,
      "p_value": 0.04839584078150508,
      "diff_mean": 0.3478425145149231,
      "diff_std": 0.10558108985424042,
      "diff_start": 0.45080018043518066,
      "diff_end": 0.205551415681839,
      "ab_corr_p": 0.8705563993026687,
      "ba_corr_p": 0.32317022898538816,
      "contagion_direction": null
    },
    "(2,1)": {
      "group_A": 2,
      "group_B": 1,
      "party_A": 0,
      "party_B": 0,
      "same_party": true,
      "total_interaction": 2532,
      "pattern": "Stability",
      "slope": 0.011982166902585464,
      "intercept": 0.08789539269425652,
      "r_squared": 0.1818909547564836,
      "p_value": 0.19084871455346866,
      "diff_mean": 0.14780622720718384,
      "diff_std": 0.08884435147047043,
      "diff_start": 0.062248289585113525,
      "diff_end": 0.17459417879581451,
      "ab_corr_p": 0.6044177807237481,
      "ba_corr_p": 0.6088357543212769,
      "contagion_direction": null
    },
    "(2,3)": {
      "group_A": 2,
      "group_B": 3,
      "party_A": 0,
      "party_B": 1,
      "same_party": false,
      "total_interaction": 119,
      "pattern": "Stability",
      "slope": -0.03018966831944206,
      "intercept": 0.6073759455572475,
      "r_squared": 0.330186905276745,
      "p_value": 0.06445371120683221,
      "diff_mean": 0.45642760396003723,
      "diff_std": 0.16614161431789398,
      "diff_start": 0.664879560470581,
      "diff_end": 0.31767988204956055,
      "ab_corr_p": 0.8280489622911942,
      "ba_corr_p": 0.2408400079977546,
      "contagion_direction": null
    },
    "(2,4)": {
      "group_A": 2,
      "group_B": 4,
      "party_A": 0,
      "party_B": 1,
      "same_party": false,
      "total_interaction": 196,
      "pattern": "Stability",
      "slope": 0.00349262763153423,
      "intercept": 0.3404556309634989,
      "r_squared": 0.036783639918047215,
      "p_value": 0.5721119929467642,
      "diff_mean": 0.35791876912117004,
      "diff_std": 0.05758706480264664,
      "diff_start": 0.31344085931777954,
      "diff_end": 0.3837912678718567,
      "ab_corr_p": 0.677052452014697,
      "ba_corr_p": 0.16095051818344516,
      "contagion_direction": null
    },
    "(2,5)": {
      "group_A": 2,
      "group_B": 5,
      "party_A": 0,
      "party_B": 0,
      "same_party": true,
      "total_interaction": 919,
      "pattern": "Stability",
      "slope": -0.013245537064292216,
      "intercept": 0.21241266619075427,
      "r_squared": 0.1989046955391242,
      "p_value": 0.16916123646975856,
      "diff_mean": 0.1461849808692932,
      "diff_std": 0.093917615711689,
      "diff_start": 0.09832438826560974,
      "diff_end": 0.057251036167144775,
      "ab_corr_p": 0.9775233481710964,
      "ba_corr_p": 0.11904274996545605,
      "contagion_direction": null
    },
    "(2,6)": {
      "group_A": 2,
      "group_B": 6,
      "party_A": 0,
      "party_B": 0,
      "same_party": true,
      "total_interaction": 15749,
      "pattern": "Stability",
      "slope": 0.004977533085779711,
      "intercept": 0.09822692044756628,
      "r_squared": 0.09786625300282646,
      "p_value": 0.3489207330648392,
      "diff_mean": 0.12311458587646484,
      "diff_std": 0.050315022468566895,
      "diff_start": 0.11920621991157532,
      "diff_end": 0.18963176012039185,
      "ab_corr_p": 0.6352377282044994,
      "ba_corr_p": 0.30018124944866115,
      "contagion_direction": null
    },
    "(3,0)": {
      "group_A": 3,
      "group_B": 0,
      "party_A": 1,
      "party_B": 1,
      "same_party": true,
      "total_interaction": 4741,
      "pattern": "Stability",
      "slope": -0.018361659212545917,
      "intercept": 0.25198849222876807,
      "r_squared": 0.2708842536903406,
      "p_value": 0.10072182208572095,
      "diff_mean": 0.1601801961660385,
      "diff_std": 0.11156296730041504,
      "diff_start": 0.2140793800354004,
      "diff_end": 0.11212846636772156,
      "ab_corr_p": 0.7725211414965671,
      "ba_corr_p": 0.916894075363082,
      "contagion_direction": null
    },
    "(3,1)": {
      "group_A": 3,
      "group_B": 1,
      "party_A": 1,
      "party_B": 0,
      "same_party": false,
      "total_interaction": 1727,
      "pattern": "Stability",
      "slope": -0.008100782470269637,
      "intercept": 0.6203306845643304,
      "r_squared": 0.023378311105982572,
      "p_value": 0.6535580190025307,
      "diff_mean": 0.5798267722129822,
      "diff_std": 0.16754072904586792,
      "diff_start": 0.6026312708854675,
      "diff_end": 0.49227404594421387,
      "ab_corr_p": 0.8976188055399844,
      "ba_corr_p": 0.5795253998251265,
      "contagion_direction": null
    },
    "(3,2)": {
      "group_A": 3,
      "group_B": 2,
      "party_A": 1,
      "party_B": 0,
      "same_party": false,
      "total_interaction": 119,
      "pattern": "Stability",
      "slope": -0.03018966831944206,
      "intercept": 0.6073759455572475,
      "r_squared": 0.330186905276745,
      "p_value": 0.06445371120683221,
      "diff_mean": 0.45642760396003723,
      "diff_std": 0.16614161431789398,
      "diff_start": 0.664879560470581,
      "diff_end": 0.31767988204956055,
      "ab_corr_p": 0.2408400079977546,
      "ba_corr_p": 0.8280489622911942,
      "contagion_direction": null
    },
    "(3,4)": {
      "group_A": 3,
      "group_B": 4,
      "party_A": 1,
      "party_B": 1,
      "same_party": true,
      "total_interaction": 935,
      "pattern": "Convergence",
      "slope": -0.026296360384334215,
      "intercept": 0.30169316178018396,
      "r_squared": 0.44777103752291036,
      "p_value": 0.024337642126931652,
      "diff_mean": 0.17021135985851288,
      "diff_std": 0.12427038699388504,
      "diff_start": 0.3514387011528015,
      "diff_end": 0.06611138582229614,
      "ab_corr_p": 0.551176567461991,
      "ba_corr_p": 0.9603576718617887,
      "contagion_direction": null
    },
    "(3,6)": {
      "group_A": 3,
      "group_B": 6,
      "party_A": 1,
      "party_B": 0,
      "same_party": false,
      "total_interaction": 425,
      "pattern": "Contagion",
      "slope": -0.00936571007425135,
      "intercept": 0.5796494307843122,
      "r_squared": 0.054451549179836585,
      "p_value": 0.48984659582632883,
      "diff_mean": 0.5328208804130554,
      "diff_std": 0.126921609044075,
      "diff_start": 0.5456733703613281,
      "diff_end": 0.5073116421699524,
      "ab_corr_p": 0.024300241759461435,
      "ba_corr_p": 0.9838299313063974,
      "contagion_direction": "3→6"
    },
    "(4,0)": {
      "group_A": 4,
      "group_B": 0,
      "party_A": 1,
      "party_B": 1,
      "same_party": true,
      "total_interaction": 1740,
      "pattern": "Stability",
      "slope": 0.006093986196951433,
      "intercept": 0.044572652063586495,
      "r_squared": 0.10004308161467212,
      "p_value": 0.34332673577964723,
      "diff_mean": 0.07504258304834366,
      "diff_std": 0.06092673912644386,
      "diff_start": 0.13735932111740112,
      "diff_end": 0.1782398521900177,
      "ab_corr_p": 0.8003064345881515,
      "ba_corr_p": 0.9338682262475769,
      "contagion_direction": null
    },
    "(4,1)": {
      "group_A": 4,
      "group_B": 1,
      "party_A": 1,
      "party_B": 0,
      "same_party": false,
      "total_interaction": 104,
      "pattern": "Stability",
      "slope": 0.025581514022567052,
      "intercept": 0.35341033745895734,
      "r_squared": 0.2451430829408968,
      "p_value": 0.12150584741547686,
      "diff_mean": 0.4813179075717926,
      "diff_std": 0.16338659822940826,
      "diff_start": 0.251192569732666,
      "diff_end": 0.55838543176651,
      "ab_corr_p": 0.6279607728838444,
      "ba_corr_p": 0.28132428636202356,
      "contagion_direction": null
    },
    "(4,2)": {
      "group_A": 4,
      "group_B": 2,
      "party_A": 1,
      "party_B": 0,
      "same_party": false,
      "total_interaction": 196,
      "pattern": "Stability",
      "slope": 0.00349262763153423,
      "intercept": 0.3404556309634989,
      "r_squared": 0.036783639918047215,
      "p_value": 0.5721119929467642,
      "diff_mean": 0.35791876912117004,
      "diff_std": 0.05758706480264664,
      "diff_start": 0.31344085931777954,
      "diff_end": 0.3837912678718567,
      "ab_corr_p": 0.16095051818344516,
      "ba_corr_p": 0.677052452014697,
      "contagion_direction": null
    },
    "(4,3)": {
      "group_A": 4,
      "group_B": 3,
      "party_A": 1,
      "party_B": 1,
      "same_party": true,
      "total_interaction": 935,
      "pattern": "Convergence",
      "slope": -0.026296360384334215,
      "intercept": 0.30169316178018396,
      "r_squared": 0.44777103752291036,
      "p_value": 0.024337642126931652,
      "diff_mean": 0.17021135985851288,
      "diff_std": 0.12427038699388504,
      "diff_start": 0.3514387011528015,
      "diff_end": 0.06611138582229614,
      "ab_corr_p": 0.9603576718617887,
      "ba_corr_p": 0.551176567461991,
      "contagion_direction": null
    },
    "(4,6)": {
      "group_A": 4,
      "group_B": 6,
      "party_A": 1,
      "party_B": 0,
      "same_party": false,
      "total_interaction": 358,
      "pattern": "Polarization",
      "slope": 0.02431658750230616,
      "intercept": 0.31272904845801264,
      "r_squared": 0.42037062144454546,
      "p_value": 0.030948453930446613,
      "diff_mean": 0.43431198596954346,
      "diff_std": 0.11860048025846481,
      "diff_start": 0.19423463940620422,
      "diff_end": 0.5734230279922485,
      "ab_corr_p": 0.8408514923120484,
      "ba_corr_p": 0.865493012171466,
      "contagion_direction": null
    },
    "(5,0)": {
      "group_A": 5,
      "group_B": 0,
      "party_A": 0,
      "party_B": 1,
      "same_party": false,
      "total_interaction": 229,
      "pattern": "Convergence",
      "slope": -0.04706827700138092,
      "intercept": 0.6381750255823135,
      "r_squared": 0.4635888384354237,
      "p_value": 0.02109041757632547,
      "diff_mean": 0.40283364057540894,
      "diff_std": 0.2186058610677719,
      "diff_start": 0.3524757921695709,
      "diff_end": 0.1483003795146942,
      "ab_corr_p": 0.46537688927399684,
      "ba_corr_p": 0.7600989396362694,
      "contagion_direction": null
    },
    "(5,1)": {
      "group_A": 5,
      "group_B": 1,
      "party_A": 0,
      "party_B": 0,
      "same_party": true,
      "total_interaction": 168,
      "pattern": "Stability",
      "slope": 0.015857798335227095,
      "intercept": 0.10905001820488411,
      "r_squared": 0.16429088123029986,
      "p_value": 0.21618954691807535,
      "diff_mean": 0.1883390098810196,
      "diff_std": 0.12371893227100372,
      "diff_start": 0.036076098680496216,
      "diff_end": 0.2318452149629593,
      "ab_corr_p": 0.553911243017114,
      "ba_corr_p": 0.7313286398131,
      "contagion_direction": null
    },
    "(5,2)": {
      "group_A": 5,
      "group_B": 2,
      "party_A": 0,
      "party_B": 0,
      "same_party": true,
      "total_interaction": 919,
      "pattern": "Stability",
      "slope": -0.013245537064292216,
      "intercept": 0.21241266619075427,
      "r_squared": 0.1989046955391242,
      "p_value": 0.16916123646975856,
      "diff_mean": 0.1461849808692932,
      "diff_std": 0.093917615711689,
      "diff_start": 0.09832438826560974,
      "diff_end": 0.057251036167144775,
      "ab_corr_p": 0.11904274996545605,
      "ba_corr_p": 0.9775233481710964,
      "contagion_direction": null
    },
    "(5,6)": {
      "group_A": 5,
      "group_B": 6,
      "party_A": 0,
      "party_B": 0,
      "same_party": true,
      "total_interaction": 965,
      "pattern": "Polarization",
      "slope": 0.019647335735234348,
      "intercept": 0.08656585351987318,
      "r_squared": 0.6061797525873306,
      "p_value": 0.0047561132846914555,
      "diff_mean": 0.18480253219604492,
      "diff_std": 0.07980000972747803,
      "diff_start": 0.020881831645965576,
      "diff_end": 0.24688279628753662,
      "ab_corr_p": 0.9032228583161421,
      "ba_corr_p": 0.8747791941316655,
      "contagion_direction": null
    },
    "(6,0)": {
      "group_A": 6,
      "group_B": 0,
      "party_A": 0,
      "party_B": 1,
      "same_party": false,
      "total_interaction": 2631,
      "pattern": "Stability",
      "slope": 0.0006098403172059493,
      "intercept": 0.4211865297772668,
      "r_squared": 0.0008561905402004092,
      "p_value": 0.9319428887938214,
      "diff_mean": 0.4242357313632965,
      "diff_std": 0.06590690463781357,
      "diff_start": 0.33159396052360535,
      "diff_end": 0.39518317580223083,
      "ab_corr_p": 0.8537381822813951,
      "ba_corr_p": 0.7635741018292965,
      "contagion_direction": null
    },
    "(6,1)": {
      "group_A": 6,
      "group_B": 1,
      "party_A": 0,
      "party_B": 0,
      "same_party": true,
      "total_interaction": 5006,
      "pattern": "Stability",
      "slope": -0.014925644140351904,
      "intercept": 0.20052071085030382,
      "r_squared": 0.21150912988781173,
      "p_value": 0.15465811618776162,
      "diff_mean": 0.1258924901485443,
      "diff_std": 0.10262862592935562,
      "diff_start": 0.05695793032646179,
      "diff_end": 0.015037573873996735,
      "ab_corr_p": 0.8385378872804171,
      "ba_corr_p": 0.6747385355530675,
      "contagion_direction": null
    },
    "(6,2)": {
      "group_A": 6,
      "group_B": 2,
      "party_A": 0,
      "party_B": 0,
      "same_party": true,
      "total_interaction": 15749,
      "pattern": "Stability",
      "slope": 0.004977533085779711,
      "intercept": 0.09822692044756628,
      "r_squared": 0.09786625300282646,
      "p_value": 0.3489207330648392,
      "diff_mean": 0.12311458587646484,
      "diff_std": 0.050315022468566895,
      "diff_start": 0.11920621991157532,
      "diff_end": 0.18963176012039185,
      "ab_corr_p": 0.30018124944866115,
      "ba_corr_p": 0.6352377282044994,
      "contagion_direction": null
    },
    "(6,3)": {
      "group_A": 6,
      "group_B": 3,
      "party_A": 0,
      "party_B": 1,
      "same_party": false,
      "total_interaction": 425,
      "pattern": "Contagion",
      "slope": -0.00936571007425135,
      "intercept": 0.5796494307843122,
      "r_squared": 0.054451549179836585,
      "p_value": 0.48984659582632883,
      "diff_mean": 0.5328208804130554,
      "diff_std": 0.126921609044075,
      "diff_start": 0.5456733703613281,
      "diff_end": 0.5073116421699524,
      "ab_corr_p": 0.9838299313063974,
      "ba_corr_p": 0.024300241759461435,
      "contagion_direction": "3→6"
    },
    "(6,4)": {
      "group_A": 6,
      "group_B": 4,
      "party_A": 0,
      "party_B": 1,
      "same_party": false,
      "total_interaction": 358,
      "pattern": "Polarization",
      "slope": 0.02431658750230616,
      "intercept": 0.31272904845801264,
      "r_squared": 0.42037062144454546,
      "p_value": 0.030948453930446613,
      "diff_mean": 0.43431198596954346,
      "diff_std": 0.11860048025846481,
      "diff_start": 0.19423463940620422,
      "diff_end": 0.5734230279922485,
      "ab_corr_p": 0.865493012171466,
      "ba_corr_p": 0.8408514923120484,
      "contagion_direction": null
    },
    "(6,5)": {
      "group_A": 6,
      "group_B": 5,
      "party_A": 0,
      "party_B": 0,
      "same_party": true,
      "total_interaction": 965,
      "pattern": "Polarization",
      "slope": 0.019647335735234348,
      "intercept": 0.08656585351987318,
      "r_squared": 0.6061797525873306,
      "p_value": 0.0047561132846914555,
      "diff_mean": 0.18480253219604492,
      "diff_std": 0.07980000972747803,
      "diff_start": 0.020881831645965576,
      "diff_end": 0.24688279628753662,
      "ab_corr_p": 0.8747791941316655,
      "ba_corr_p": 0.9032228583161421,
      "contagion_direction": null
    }
  },
  "pattern_counts": {
    "Convergence": 6,
    "Polarization": 4,
    "Contagion": 2,
    "Stability": 26
  },
  "same_party_patterns": {
    "Convergence": 2,
    "Polarization": 2,
    "Contagion": 0,
    "Stability": 14
  },
  "cross_party_patterns": {
    "Convergence": 4,
    "Polarization": 2,
    "Contagion": 2,
    "Stability": 12
  }
}